{
  "tags": [
    {
      "slug": "poetic-form",
      "title": "Poetic Form",
      "cover_image": "",
      "preview": "Lectures exploring various poetic forms, structures, and their literary significance.",
      "date": "2025-06-24",
      "status": "Active",
      "confidence": "certain",
      "importance": 9
    },
    {
      "slug": "verse",
      "title": "Verse",
      "cover_image": "",
      "preview": "Comprehensive study of verse forms, meter, and poetic techniques.",
      "date": "2025-06-24",
      "status": "Active",
      "confidence": "certain",
      "importance": 8
    }
  ]
}