[
{
    "id": "1",
    "name": "Winona Ryder",
    "image": "https://krisyotam.com/doc/imgs/people/actors/winona-ryder.jpg"
},
{
    "id": "2",
    "name": "Jodie Foster",
    "image": "https://external-content.duckduckgo.com/iu/?u=https%3A%2F%2Fi.pinimg.com%2Foriginals%2F25%2Fca%2F7c%2F25ca7c79b20885d436f91aeeb7df7351.jpg&f=1&nofb=1&ipt=a2da4f24accd0187fa92625edaecaff8b07c8d594f34a9394f7179cfcec2fd0a"
},
{
    "id": "3",
    "name": "Louise Brooks",
    "image": "https://2.bp.blogspot.com/-e6kHG4R9VGw/V1cEmP3EvII/AAAAAAAAChc/x62KIKYMQIgRRYVawParPgYxplLtckAggCK4B/s1600/Louise%2BBrooks%252C%2BC.1930%25E2%2580%2599s.jpg"
},
{
    "id": "4",
    "name": "Audrey Hepburn",
    "image": "https://upload.wikimedia.org/wikipedia/commons/thumb/a/ae/Audrey_Hepburn_in_Roman_Holiday_%28cropped%29.jpg/330px-Audrey_Hepburn_in_Roman_Holiday_%28cropped%29.jpg"
},
{
    "id": "5",
    "name": "Denzel Washington",
    "image": "https://assets.mycast.io/actor_images/actor-denzel-washington-188288_large.jpg?1616209347"
},
{
    "id": "6",
    "name": "Meryl Streep",
    "image": "https://i.postimg.cc/6QwXNxw2/meryl-streep.jpg"
},
{
    "id": "7",
    "name": "Morgan Freeman",
    "image": "https://i.postimg.cc/HkMYgtyK/morgan-freeman.jpg"
},
{
    "id": "8",
    "name": "Jenna Ortega",
    "image": "https://i.postimg.cc/8C8hpwnr/jenna-ortega.jpg"
},
{
    "id": "9",
    "name": "Nicole Kidman",
    "image": "https://m.media-amazon.com/images/M/MV5BMTk1MjM5NDg4MF5BMl5BanBnXkFtZTcwNDg1OTQ4Nw@@._V1_FMjpg_UX1000_.jpg"
},
{
    "id": "10",
    "name": "Angelina Jolie",
    "image": "https://i.postimg.cc/FKB1FKKC/angelina-jolie.webp"
},
{
    "id": "11",
    "name": "Brad Pitt",
    "image": "/placeholder.svg?height=150&width=150"
},
{
    "id": "12",
    "name": "Emma Stone",
    "image": "/placeholder.svg?height=150&width=150"
},
{
    "id": "13",
    "name": "Joaquin Phoenix",
    "image": "/placeholder.svg?height=150&width=150"
},
{
    "id": "14",
    "name": "Frances McDormand",
    "image": "/placeholder.svg?height=150&width=150"
},
{
    "id": "15",
    "name": "Daniel Day-Lewis",
    "image": "/placeholder.svg?height=150&width=150"
},
{
    "id": "16",
    "name": "Édith Scob",
    "image": "/placeholder.svg?height=150&width=150"
},
{
    "id": "17",
    "name": "Katherine Hepburn",
    ",image": "https://i.postimg.cc/c1nxmBVb/katherine-hepburn.jpg"
},
{
    "id": "18",
    "name": "Marilyn Monroe",
    "image": "https://upload.wikimedia.org/wikipedia/commons/thumb/c/ca/Marilyn_Monroe%2C_Photoplay_1953.jpg/250px-Marilyn_Monroe%2C_Photoplay_1953.jpg"
},
{
    "id": "19",
    "name": "Leonardo DiCaprio",
    "image": "https://i.postimg.cc/xCfnLD4D/leonardo-dicaprio.webp"
}
]