{
  "symbols": [
    {
      "id": "alpha",
      "name": "Alpha",
      "symbol": "α",
      "category": "Greek Letters",
      "description": "First letter of the Greek alphabet, commonly used in mathematics and physics",
      "unicodeValue": "U+03B1",
      "htmlEntity": "&alpha;",
      "contexts": ["Mathematics", "Physics", "Statistics"],
      "commonUses": ["Angle measurement", "Angular acceleration", "Alpha particles", "Significance level in statistics"],
      "related": ["beta", "gamma", "theta"],
      "examples": ["α = 30° (angle)", "α-decay (nuclear physics)", "α = 0.05 (significance level)"]
    },
    {
      "id": "beta",
      "name": "Beta",
      "symbol": "β",
      "category": "Greek Letters",
      "description": "Second letter of the Greek alphabet, used in various mathematical and scientific contexts",
      "unicodeValue": "U+03B2",
      "htmlEntity": "&beta;",
      "contexts": ["Mathematics", "Physics", "Statistics", "Finance"],
      "commonUses": ["Beta function", "Beta distribution", "Beta particles", "Market beta in finance"],
      "related": ["alpha", "gamma", "delta"],
      "examples": ["β(x,y) = Beta function", "β-decay (nuclear physics)", "Stock β = 1.2 (finance)"]
    },
    {
      "id": "gamma",
      "name": "Gamma",
      "symbol": "γ",
      "category": "Greek Letters",
      "description": "Third letter of the Greek alphabet, widely used in mathematics and physics",
      "unicodeValue": "U+03B3",
      "htmlEntity": "&gamma;",
      "contexts": ["Mathematics", "Physics", "Engineering"],
      "commonUses": ["Gamma function", "Lorentz factor", "Surface tension", "Euler-Mascheroni constant"],
      "related": ["alpha", "beta", "delta"],
      "examples": ["γ = 0.5772... (Euler-Mascheroni constant)", "γ = 1/√(1-v²/c²) (Lorentz factor)", "Γ(n) = (n-1)! (Gamma function)"]
    },
    {
      "id": "delta",
      "name": "Delta",
      "symbol": "δ",
      "category": "Greek Letters",
      "description": "Fourth letter of the Greek alphabet, representing change or difference",
      "unicodeValue": "U+03B4",
      "htmlEntity": "&delta;",
      "contexts": ["Mathematics", "Physics", "Engineering", "Chemistry"],
      "commonUses": ["Change in a variable", "Dirac delta function", "Partial derivative", "Chemical shift"],
      "related": ["epsilon", "nabla", "partial"],
      "examples": ["Δx = change in x", "δ(x) = Dirac delta function", "∂f/∂x = partial derivative"]
    },
    {
      "id": "epsilon",
      "name": "Epsilon",
      "symbol": "ε",
      "category": "Greek Letters",
      "description": "Fifth letter of the Greek alphabet, often representing small quantities",
      "unicodeValue": "U+03B5",
      "htmlEntity": "&epsilon;",
      "contexts": ["Mathematics", "Physics", "Analysis"],
      "commonUses": ["Small positive number", "Strain in mechanics", "Permittivity", "Error term"],
      "related": ["delta", "eta", "limit"],
      "examples": ["∀ε > 0 (for all epsilon greater than zero)", "ε₀ = permittivity of free space", "stress-strain: σ = Eε"]
    },
    {
      "id": "theta",
      "name": "Theta",
      "symbol": "θ",
      "category": "Greek Letters",
      "description": "Eighth letter of the Greek alphabet, commonly used for angles",
      "unicodeValue": "U+03B8",
      "htmlEntity": "&theta;",
      "contexts": ["Mathematics", "Physics", "Trigonometry"],
      "commonUses": ["Angle measurement", "Polar coordinates", "Spherical coordinates", "Big O notation"],
      "related": ["alpha", "phi", "pi"],
      "examples": ["θ = 45° (angle)", "(r, θ) polar coordinates", "Θ(n²) big theta notation"]
    },
    {
      "id": "pi",
      "name": "Pi",
      "symbol": "π",
      "category": "Greek Letters",
      "description": "Sixteenth letter of the Greek alphabet, mathematical constant ≈ 3.14159",
      "unicodeValue": "U+03C0",
      "htmlEntity": "&pi;",
      "contexts": ["Mathematics", "Geometry", "Physics"],
      "commonUses": ["Circle circumference", "Area calculations", "Trigonometric functions", "Fourier analysis"],
      "related": ["e", "tau", "circle"],
      "examples": ["C = 2πr (circumference)", "A = πr² (area of circle)", "e^(iπ) + 1 = 0 (Euler's identity)"]
    },
    {
      "id": "sigma",
      "name": "Sigma",
      "symbol": "σ",
      "category": "Greek Letters",
      "description": "Eighteenth letter of the Greek alphabet, used for summation and standard deviation",
      "unicodeValue": "U+03C3",
      "htmlEntity": "&sigma;",
      "contexts": ["Mathematics", "Statistics", "Physics"],
      "commonUses": ["Standard deviation", "Stress in mechanics", "Conductivity", "Stefan-Boltzmann constant"],
      "related": ["sum", "variance", "mu"],
      "examples": ["σ = standard deviation", "σ = F/A (stress)", "∑ᵢ₌₁ⁿ xᵢ (summation)"]
    },
    {
      "id": "phi",
      "name": "Phi",
      "symbol": "φ",
      "category": "Greek Letters",
      "description": "Twenty-first letter of the Greek alphabet, golden ratio ≈ 1.618",
      "unicodeValue": "U+03C6",
      "htmlEntity": "&phi;",
      "contexts": ["Mathematics", "Art", "Nature", "Physics"],
      "commonUses": ["Golden ratio", "Euler's totient function", "Phase angle", "Electric potential"],
      "related": ["golden-ratio", "fibonacci", "theta"],
      "examples": ["φ = (1+√5)/2 ≈ 1.618", "φ(n) = Euler's totient function", "V = φ (electric potential)"]
    },
    {
      "id": "omega",
      "name": "Omega",
      "symbol": "ω",
      "category": "Greek Letters",
      "description": "Last letter of the Greek alphabet, often representing angular frequency",
      "unicodeValue": "U+03C9",
      "htmlEntity": "&omega;",
      "contexts": ["Physics", "Engineering", "Mathematics"],
      "commonUses": ["Angular frequency", "Angular velocity", "Resistance (ohm)", "Big O notation"],
      "related": ["frequency", "ohm", "big-o"],
      "examples": ["ω = 2πf (angular frequency)", "Ω = resistance unit", "Ω(n) big omega notation"]
    },
    {
      "id": "infinity",
      "name": "Infinity",
      "symbol": "∞",
      "category": "Mathematical Operators",
      "description": "Symbol representing unlimited or boundless quantity",
      "unicodeValue": "U+221E",
      "htmlEntity": "&infin;",
      "contexts": ["Mathematics", "Calculus", "Set Theory"],
      "commonUses": ["Limits", "Infinite series", "Unbounded sets", "Asymptotic behavior"],
      "related": ["limit", "series", "unbounded"],
      "examples": ["lim(x→∞) f(x)", "∑ᵢ₌₁^∞ aᵢ (infinite series)", "(-∞, ∞) real number line"]
    },
    {
      "id": "integral",
      "name": "Integral",
      "symbol": "∫",
      "category": "Mathematical Operators",
      "description": "Symbol for integration in calculus",
      "unicodeValue": "U+222B",
      "htmlEntity": "&int;",
      "contexts": ["Calculus", "Mathematics", "Physics"],
      "commonUses": ["Definite integrals", "Indefinite integrals", "Area under curves", "Volume calculations"],
      "related": ["derivative", "antiderivative", "area"],
      "examples": ["∫ f(x)dx (indefinite integral)", "∫ₐᵇ f(x)dx (definite integral)", "∬ f(x,y)dxdy (double integral)"]
    },
    {
      "id": "partial",
      "name": "Partial Derivative",
      "symbol": "∂",
      "category": "Mathematical Operators",
      "description": "Symbol for partial differentiation",
      "unicodeValue": "U+2202",
      "htmlEntity": "&part;",
      "contexts": ["Calculus", "Physics", "Engineering"],
      "commonUses": ["Partial derivatives", "Multivariable calculus", "Differential equations", "Gradient calculations"],
      "related": ["gradient", "derivative", "nabla"],
      "examples": ["∂f/∂x (partial derivative)", "∂²f/∂x² (second partial)", "∇f = (∂f/∂x, ∂f/∂y, ∂f/∂z)"]
    },
    {
      "id": "nabla",
      "name": "Nabla",
      "symbol": "∇",
      "category": "Mathematical Operators",
      "description": "Vector differential operator (del operator)",
      "unicodeValue": "U+2207",
      "htmlEntity": "&nabla;",
      "contexts": ["Vector Calculus", "Physics", "Engineering"],
      "commonUses": ["Gradient", "Divergence", "Curl", "Laplacian"],
      "related": ["gradient", "divergence", "curl", "partial"],
      "examples": ["∇f = gradient of f", "∇·F = divergence of F", "∇×F = curl of F", "∇²f = Laplacian of f"]
    },
    {
      "id": "sum",
      "name": "Summation",
      "symbol": "∑",
      "category": "Mathematical Operators",
      "description": "Symbol for summation of terms",
      "unicodeValue": "U+2211",
      "htmlEntity": "&sum;",
      "contexts": ["Mathematics", "Statistics", "Discrete Math"],
      "commonUses": ["Finite sums", "Infinite series", "Statistical formulas", "Sequence operations"],
      "related": ["sigma", "series", "sequence"],
      "examples": ["∑ᵢ₌₁ⁿ i = n(n+1)/2", "∑ᵢ₌₀^∞ xⁱ = 1/(1-x)", "x̄ = (1/n)∑ᵢ₌₁ⁿ xᵢ"]
    },
    {
      "id": "product",
      "name": "Product",
      "symbol": "∏",
      "category": "Mathematical Operators",
      "description": "Symbol for multiplication of terms",
      "unicodeValue": "U+220F",
      "htmlEntity": "&prod;",
      "contexts": ["Mathematics", "Combinatorics", "Number Theory"],
      "commonUses": ["Finite products", "Factorials", "Probability calculations", "Infinite products"],
      "related": ["factorial", "multiplication", "sum"],
      "examples": ["∏ᵢ₌₁ⁿ i = n!", "∏ᵢ₌₁ⁿ (1+xᵢ)", "π = 4∏ₙ₌₁^∞ (1-1/(2n+1)²)"]
    },
    {
      "id": "element-of",
      "name": "Element Of",
      "symbol": "∈",
      "category": "Set Theory",
      "description": "Symbol indicating membership in a set",
      "unicodeValue": "U+2208",
      "htmlEntity": "&isin;",
      "contexts": ["Set Theory", "Mathematics", "Logic"],
      "commonUses": ["Set membership", "Mathematical proofs", "Domain specification", "Logical statements"],
      "related": ["subset", "not-element-of", "set"],
      "examples": ["x ∈ A (x is in set A)", "2 ∈ ℕ (2 is a natural number)", "∀x ∈ ℝ (for all x in real numbers)"]
    },
    {
      "id": "subset",
      "name": "Subset",
      "symbol": "⊆",
      "category": "Set Theory",
      "description": "Symbol indicating one set is contained in another",
      "unicodeValue": "U+2286",
      "htmlEntity": "&sube;",
      "contexts": ["Set Theory", "Mathematics", "Logic"],
      "commonUses": ["Set inclusion", "Mathematical proofs", "Hierarchy relationships", "Category theory"],
      "related": ["element-of", "proper-subset", "superset"],
      "examples": ["A ⊆ B (A is subset of B)", "ℕ ⊆ ℤ ⊆ ℚ ⊆ ℝ", "∅ ⊆ A (empty set subset)"]
    },
    {
      "id": "union",
      "name": "Union",
      "symbol": "∪",
      "category": "Set Theory",
      "description": "Symbol for set union operation",
      "unicodeValue": "U+222A",
      "htmlEntity": "&cup;",
      "contexts": ["Set Theory", "Mathematics", "Logic"],
      "commonUses": ["Set combinations", "Probability theory", "Boolean algebra", "Database operations"],
      "related": ["intersection", "complement", "set"],
      "examples": ["A ∪ B (union of A and B)", "P(A ∪ B) = P(A) + P(B) - P(A ∩ B)", "⋃ᵢ₌₁ⁿ Aᵢ (union of sets)"]
    },
    {
      "id": "intersection",
      "name": "Intersection",
      "symbol": "∩",
      "category": "Set Theory",
      "description": "Symbol for set intersection operation",
      "unicodeValue": "U+2229",
      "htmlEntity": "&cap;",
      "contexts": ["Set Theory", "Mathematics", "Logic"],
      "commonUses": ["Common elements", "Probability theory", "Boolean algebra", "Database operations"],
      "related": ["union", "complement", "set"],
      "examples": ["A ∩ B (intersection of A and B)", "P(A ∩ B) = P(A) × P(B|A)", "⋂ᵢ₌₁ⁿ Aᵢ (intersection of sets)"]
    },
    {
      "id": "implies",
      "name": "Implies",
      "symbol": "⟹",
      "category": "Logic",
      "description": "Symbol for logical implication",
      "unicodeValue": "U+27F9",
      "htmlEntity": "&rArr;",
      "contexts": ["Logic", "Mathematics", "Proofs"],
      "commonUses": ["Logical deduction", "Mathematical proofs", "Conditional statements", "Theorem statements"],
      "related": ["if-and-only-if", "therefore", "because"],
      "examples": ["P ⟹ Q (P implies Q)", "x > 0 ⟹ x² > 0", "A ⊆ B ⟹ A ∩ B = A"]
    },
    {
      "id": "equivalent",
      "name": "If and Only If",
      "symbol": "⟺",
      "category": "Logic",
      "description": "Symbol for logical equivalence (biconditional)",
      "unicodeValue": "U+27FA",
      "htmlEntity": "&hArr;",
      "contexts": ["Logic", "Mathematics", "Proofs"],
      "commonUses": ["Logical equivalence", "Definitions", "Necessary and sufficient conditions", "Biconditional statements"],
      "related": ["implies", "equivalent", "definition"],
      "examples": ["P ⟺ Q (P if and only if Q)", "x = 0 ⟺ x² = 0", "A = B ⟺ A ⊆ B ∧ B ⊆ A"]
    },
    {
      "id": "for-all",
      "name": "For All",
      "symbol": "∀",
      "category": "Logic",
      "description": "Universal quantifier symbol",
      "unicodeValue": "U+2200",
      "htmlEntity": "&forall;",
      "contexts": ["Logic", "Mathematics", "Set Theory"],
      "commonUses": ["Universal statements", "Mathematical proofs", "Predicate logic", "General theorems"],
      "related": ["exists", "quantifier", "logic"],
      "examples": ["∀x ∈ ℝ, x² ≥ 0", "∀ε > 0, ∃δ > 0...", "∀n ∈ ℕ, n! ≥ 1"]
    },
    {
      "id": "exists",
      "name": "There Exists",
      "symbol": "∃",
      "category": "Logic",
      "description": "Existential quantifier symbol",
      "unicodeValue": "U+2203",
      "htmlEntity": "&exist;",
      "contexts": ["Logic", "Mathematics", "Set Theory"],
      "commonUses": ["Existence statements", "Mathematical proofs", "Predicate logic", "Constructive proofs"],
      "related": ["for-all", "unique-exists", "quantifier"],
      "examples": ["∃x ∈ ℝ such that x² = 2", "∃! (there exists unique)", "∃n ∈ ℕ, n > 1000"]
    },
    {
      "id": "therefore",
      "name": "Therefore",
      "symbol": "∴",
      "category": "Logic",
      "description": "Symbol indicating logical conclusion",
      "unicodeValue": "U+2234",
      "htmlEntity": "&there4;",
      "contexts": ["Logic", "Mathematics", "Proofs"],
      "commonUses": ["Drawing conclusions", "Mathematical proofs", "Logical arguments", "QED statements"],
      "related": ["because", "implies", "conclusion"],
      "examples": ["x = 2, y = 3 ∴ x + y = 5", "All men are mortal ∴ Socrates is mortal", "A ⊆ B, B ⊆ C ∴ A ⊆ C"]
    },
    {
      "id": "because",
      "name": "Because",
      "symbol": "∵",
      "category": "Logic",
      "description": "Symbol indicating logical reason",
      "unicodeValue": "U+2235",
      "htmlEntity": "&becaus;",
      "contexts": ["Logic", "Mathematics", "Proofs"],
      "commonUses": ["Providing reasons", "Mathematical justification", "Logical arguments", "Proof steps"],
      "related": ["therefore", "implies", "reason"],
      "examples": ["x + y = 5 ∵ x = 2, y = 3", "f is continuous ∵ f is differentiable", "A = B ∵ A ⊆ B and B ⊆ A"]
    },
    {
      "id": "eta",
      "name": "Eta",
      "symbol": "η",
      "category": "Greek Letters",
      "description": "Seventh letter of the Greek alphabet, often used for efficiency",
      "unicodeValue": "U+03B7",
      "htmlEntity": "&eta;",
      "contexts": ["Physics", "Engineering", "Mathematics"],
      "commonUses": ["Efficiency", "Viscosity", "Conformal mappings", "Dirichlet eta function"],
      "related": ["epsilon", "theta", "zeta"],
      "examples": ["η = efficiency = output/input", "η = dynamic viscosity", "η(s) = Dirichlet eta function"]
    },
    {
      "id": "zeta",
      "name": "Zeta",
      "symbol": "ζ",
      "category": "Greek Letters",
      "description": "Sixth letter of the Greek alphabet, famous for Riemann zeta function",
      "unicodeValue": "U+03B6",
      "htmlEntity": "&zeta;",
      "contexts": ["Mathematics", "Number Theory", "Analysis"],
      "commonUses": ["Riemann zeta function", "Damping ratio", "Weierstrass zeta function", "Coordinate systems"],
      "related": ["eta", "xi", "riemann"],
      "examples": ["ζ(s) = Riemann zeta function", "ζ = damping ratio", "ζ(2) = π²/6"]
    },
    {
      "id": "iota",
      "name": "Iota",
      "symbol": "ι",
      "category": "Greek Letters",
      "description": "Ninth letter of the Greek alphabet, often representing small quantities",
      "unicodeValue": "U+03B9",
      "htmlEntity": "&iota;",
      "contexts": ["Mathematics", "Logic", "Programming"],
      "commonUses": ["Small quantities", "Index notation", "Iota operator", "Complex analysis"],
      "related": ["epsilon", "delta", "small"],
      "examples": ["ι = small increment", "ι(P) = iota operator", "minimal ι change"]
    },
    {
      "id": "kappa",
      "name": "Kappa",
      "symbol": "κ",
      "category": "Greek Letters",
      "description": "Tenth letter of the Greek alphabet, used for curvature and dielectric constant",
      "unicodeValue": "U+03BA",
      "htmlEntity": "&kappa;",
      "contexts": ["Mathematics", "Physics", "Statistics"],
      "commonUses": ["Curvature", "Dielectric constant", "Cohen's kappa", "Thermal conductivity"],
      "related": ["curvature", "conductivity", "statistics"],
      "examples": ["κ = curvature of surface", "κ = dielectric constant", "κ = Cohen's kappa coefficient"]
    },
    {
      "id": "lambda",
      "name": "Lambda",
      "symbol": "λ",
      "category": "Greek Letters",
      "description": "Eleventh letter of the Greek alphabet, used for wavelength and eigenvalues",
      "unicodeValue": "U+03BB",
      "htmlEntity": "&lambda;",
      "contexts": ["Physics", "Mathematics", "Computer Science"],
      "commonUses": ["Wavelength", "Eigenvalues", "Lambda calculus", "Decay constant"],
      "related": ["eigenvalue", "wavelength", "calculus"],
      "examples": ["λ = 550 nm (wavelength)", "Aν = λν (eigenvalue equation)", "λx.x+1 (lambda function)"]
    },
    {
      "id": "mu",
      "name": "Mu",
      "symbol": "μ",
      "category": "Greek Letters",
      "description": "Twelfth letter of the Greek alphabet, used for mean and friction coefficient",
      "unicodeValue": "U+03BC",
      "htmlEntity": "&mu;",
      "contexts": ["Statistics", "Physics", "Engineering"],
      "commonUses": ["Population mean", "Friction coefficient", "Magnetic permeability", "Micro prefix"],
      "related": ["mean", "friction", "statistics"],
      "examples": ["μ = population mean", "μ = coefficient of friction", "μ₀ = permeability of free space"]
    },
    {
      "id": "nu",
      "name": "Nu",
      "symbol": "ν",
      "category": "Greek Letters",
      "description": "Thirteenth letter of the Greek alphabet, used for frequency and degrees of freedom",
      "unicodeValue": "U+03BD",
      "htmlEntity": "&nu;",
      "contexts": ["Physics", "Statistics", "Engineering"],
      "commonUses": ["Frequency", "Degrees of freedom", "Kinematic viscosity", "Neutrino"],
      "related": ["frequency", "statistics", "physics"],
      "examples": ["ν = frequency in Hz", "ν = degrees of freedom", "ν_e = electron neutrino"]
    },
    {
      "id": "xi",
      "name": "Xi",
      "symbol": "ξ",
      "category": "Greek Letters",
      "description": "Fourteenth letter of the Greek alphabet, often used as a variable",
      "unicodeValue": "U+03BE",
      "htmlEntity": "&xi;",
      "contexts": ["Mathematics", "Physics", "Statistics"],
      "commonUses": ["Random variable", "Coordinate variable", "Coherence length", "Riemann xi function"],
      "related": ["variable", "coordinate", "random"],
      "examples": ["ξ = random variable", "ξ(s) = Riemann xi function", "correlation length ξ"]
    },
    {
      "id": "omicron",
      "name": "Omicron",
      "symbol": "ο",
      "category": "Greek Letters",
      "description": "Fifteenth letter of the Greek alphabet, rarely used in mathematics",
      "unicodeValue": "U+03BF",
      "htmlEntity": "&omicron;",
      "contexts": ["Mathematics", "Astronomy"],
      "commonUses": ["Star designation", "Little O notation", "Variable naming"],
      "related": ["omega", "notation", "astronomy"],
      "examples": ["ο Ceti (star name)", "o(n) little o notation"]
    },
    {
      "id": "rho",
      "name": "Rho",
      "symbol": "ρ",
      "category": "Greek Letters",
      "description": "Seventeenth letter of the Greek alphabet, used for density and correlation",
      "unicodeValue": "U+03C1",
      "htmlEntity": "&rho;",
      "contexts": ["Physics", "Statistics", "Engineering"],
      "commonUses": ["Density", "Correlation coefficient", "Resistivity", "Charge density"],
      "related": ["density", "correlation", "resistivity"],
      "examples": ["ρ = density = m/V", "ρ = correlation coefficient", "ρ = electrical resistivity"]
    },
    {
      "id": "tau",
      "name": "Tau",
      "symbol": "τ",
      "category": "Greek Letters",
      "description": "Nineteenth letter of the Greek alphabet, equal to 2π",
      "unicodeValue": "U+03C4",
      "htmlEntity": "&tau;",
      "contexts": ["Mathematics", "Physics", "Engineering"],
      "commonUses": ["Time constant", "Tau (2π)", "Proper time", "Torque"],
      "related": ["pi", "time", "torque"],
      "examples": ["τ = 2π ≈ 6.283", "τ = RC (time constant)", "τ = torque = r × F"]
    },
    {
      "id": "upsilon",
      "name": "Upsilon",
      "symbol": "υ",
      "category": "Greek Letters",
      "description": "Twentieth letter of the Greek alphabet, used in particle physics",
      "unicodeValue": "U+03C5",
      "htmlEntity": "&upsilon;",
      "contexts": ["Physics", "Particle Physics"],
      "commonUses": ["Upsilon meson", "Velocity component", "Particle designation"],
      "related": ["particle", "physics", "meson"],
      "examples": ["Υ meson (upsilon meson)", "υ = velocity component"]
    },
    {
      "id": "chi",
      "name": "Chi",
      "symbol": "χ",
      "category": "Greek Letters",
      "description": "Twenty-second letter of the Greek alphabet, used in statistics and physics",
      "unicodeValue": "U+03C7",
      "htmlEntity": "&chi;",
      "contexts": ["Statistics", "Physics", "Mathematics"],
      "commonUses": ["Chi-squared test", "Magnetic susceptibility", "Euler characteristic", "Character function"],
      "related": ["statistics", "test", "susceptibility"],
      "examples": ["χ² = chi-squared statistic", "χ = magnetic susceptibility", "χ(G) = Euler characteristic"]
    },
    {
      "id": "psi",
      "name": "Psi",
      "symbol": "ψ",
      "category": "Greek Letters",
      "description": "Twenty-third letter of the Greek alphabet, used for wave functions",
      "unicodeValue": "U+03C8",
      "htmlEntity": "&psi;",
      "contexts": ["Physics", "Quantum Mechanics", "Psychology"],
      "commonUses": ["Wave function", "Quantum state", "Psychology symbol", "Stream function"],
      "related": ["quantum", "wave", "psychology"],
      "examples": ["ψ(x) = wave function", "Ψ = quantum state vector", "ψ = stream function"]
    },
    {
      "id": "not-equal",
      "name": "Not Equal",
      "symbol": "≠",
      "category": "Mathematical Operators",
      "description": "Symbol indicating inequality",
      "unicodeValue": "U+2260",
      "htmlEntity": "&ne;",
      "contexts": ["Mathematics", "Logic", "Programming"],
      "commonUses": ["Inequality", "Comparison", "Logical negation", "Set difference"],
      "related": ["equal", "inequality", "comparison"],
      "examples": ["x ≠ y (x not equal to y)", "A ≠ B (sets are different)", "3 ≠ 5"]
    },
    {
      "id": "less-than-equal",
      "name": "Less Than or Equal",
      "symbol": "≤",
      "category": "Mathematical Operators",
      "description": "Symbol for less than or equal to relation",
      "unicodeValue": "U+2264",
      "htmlEntity": "&le;",
      "contexts": ["Mathematics", "Logic", "Programming"],
      "commonUses": ["Inequalities", "Bounds", "Ordering relations", "Constraints"],
      "related": ["less-than", "inequality", "ordering"],
      "examples": ["x ≤ 5 (x at most 5)", "0 ≤ p ≤ 1 (probability bounds)", "f(x) ≤ g(x)"]
    },
    {
      "id": "greater-than-equal",
      "name": "Greater Than or Equal",
      "symbol": "≥",
      "category": "Mathematical Operators",
      "description": "Symbol for greater than or equal to relation",
      "unicodeValue": "U+2265",
      "htmlEntity": "&ge;",
      "contexts": ["Mathematics", "Logic", "Programming"],
      "commonUses": ["Inequalities", "Bounds", "Ordering relations", "Constraints"],
      "related": ["greater-than", "inequality", "ordering"],
      "examples": ["x ≥ 0 (x non-negative)", "n ≥ 1 (positive integer)", "||x|| ≥ 0 (norm property)"]
    },
    {
      "id": "approximately",
      "name": "Approximately Equal",
      "symbol": "≈",
      "category": "Mathematical Operators",
      "description": "Symbol indicating approximate equality",
      "unicodeValue": "U+2248",
      "htmlEntity": "&asymp;",
      "contexts": ["Mathematics", "Science", "Engineering"],
      "commonUses": ["Approximations", "Numerical estimates", "Asymptotic behavior", "Rounding"],
      "related": ["equal", "approximate", "estimate"],
      "examples": ["π ≈ 3.14159", "e ≈ 2.718", "√2 ≈ 1.414"]
    },
    {
      "id": "much-less",
      "name": "Much Less Than",
      "symbol": "≪",
      "category": "Mathematical Operators",
      "description": "Symbol indicating much smaller than relation",
      "unicodeValue": "U+226A",
      "htmlEntity": "&ll;",
      "contexts": ["Mathematics", "Physics", "Asymptotic Analysis"],
      "commonUses": ["Asymptotic comparisons", "Order of magnitude", "Limit analysis", "Big O notation"],
      "related": ["much-greater", "asymptotic", "order"],
      "examples": ["1 ≪ n (1 much less than n)", "ε ≪ 1 (epsilon small)", "x ≪ y for large y"]
    },
    {
      "id": "much-greater",
      "name": "Much Greater Than",
      "symbol": "≫",
      "category": "Mathematical Operators",
      "description": "Symbol indicating much larger than relation",
      "unicodeValue": "U+226B",
      "htmlEntity": "&gg;",
      "contexts": ["Mathematics", "Physics", "Asymptotic Analysis"],
      "commonUses": ["Asymptotic comparisons", "Order of magnitude", "Limit analysis", "Big O notation"],
      "related": ["much-less", "asymptotic", "order"],
      "examples": ["n ≫ 1 (n much greater than 1)", "N ≫ k for large N", "temperature ≫ 0K"]
    },
    {
      "id": "plus-minus",
      "name": "Plus-Minus",
      "symbol": "±",
      "category": "Mathematical Operators",
      "description": "Symbol indicating plus or minus",
      "unicodeValue": "U+00B1",
      "htmlEntity": "&plusmn;",
      "contexts": ["Mathematics", "Statistics", "Physics"],
      "commonUses": ["Uncertainty", "Error margins", "Quadratic solutions", "Confidence intervals"],
      "related": ["uncertainty", "error", "interval"],
      "examples": ["x = (-b ± √(b²-4ac))/2a", "5.2 ± 0.1 (measurement)", "±3σ confidence interval"]
    },
    {
      "id": "minus-plus",
      "name": "Minus-Plus",
      "symbol": "∓",
      "category": "Mathematical Operators",
      "description": "Symbol indicating minus or plus (opposite of ±)",
      "unicodeValue": "U+2213",
      "htmlEntity": "&mnplus;",
      "contexts": ["Mathematics", "Physics"],
      "commonUses": ["Opposite sign to ±", "Conjugate expressions", "Alternative solutions"],
      "related": ["plus-minus", "conjugate", "alternative"],
      "examples": ["x ± y, z ∓ y", "(a ± b)(a ∓ b) = a² - b²"]
    },
    {
      "id": "square-root",
      "name": "Square Root",
      "symbol": "√",
      "category": "Mathematical Operators",
      "description": "Symbol for square root operation",
      "unicodeValue": "U+221A",
      "htmlEntity": "&radic;",
      "contexts": ["Mathematics", "Algebra", "Calculus"],
      "commonUses": ["Square roots", "Radical expressions", "Distance formulas", "Quadratic solutions"],
      "related": ["root", "radical", "power"],
      "examples": ["√16 = 4", "√(x² + y²) = distance", "√2 ≈ 1.414"]
    },
    {
      "id": "proportional",
      "name": "Proportional To",
      "symbol": "∝",
      "category": "Mathematical Operators",
      "description": "Symbol indicating proportionality",
      "unicodeValue": "U+221D",
      "htmlEntity": "&prop;",
      "contexts": ["Mathematics", "Physics", "Statistics"],
      "commonUses": ["Direct proportionality", "Scaling relationships", "Physical laws", "Statistical relationships"],
      "related": ["proportion", "scaling", "relationship"],
      "examples": ["F ∝ ma (force proportional to mass×acceleration)", "y ∝ x (y proportional to x)", "P ∝ T (pressure proportional to temperature)"]
    },
    {
      "id": "angle",
      "name": "Angle",
      "symbol": "∠",
      "category": "Geometric Symbols",
      "description": "Symbol representing an angle",
      "unicodeValue": "U+2220",
      "htmlEntity": "&ang;",
      "contexts": ["Geometry", "Trigonometry", "Mathematics"],
      "commonUses": ["Angle notation", "Geometric proofs", "Trigonometry", "Vector directions"],
      "related": ["triangle", "degree", "radian"],
      "examples": ["∠ABC = 90°", "∠θ = angle theta", "∠(u,v) = angle between vectors"]
    },
    {
      "id": "parallel",
      "name": "Parallel",
      "symbol": "∥",
      "category": "Geometric Symbols",
      "description": "Symbol indicating parallel lines or vectors",
      "unicodeValue": "U+2225",
      "htmlEntity": "&par;",
      "contexts": ["Geometry", "Linear Algebra", "Physics"],
      "commonUses": ["Parallel lines", "Parallel vectors", "Parallel processing", "Geometric relationships"],
      "related": ["perpendicular", "geometry", "vector"],
      "examples": ["AB ∥ CD (lines parallel)", "u ∥ v (vectors parallel)", "a ∥ b (parallel elements)"]
    },
    {
      "id": "perpendicular",
      "name": "Perpendicular",
      "symbol": "⊥",
      "category": "Geometric Symbols",
      "description": "Symbol indicating perpendicular lines or orthogonality",
      "unicodeValue": "U+22A5",
      "htmlEntity": "&perp;",
      "contexts": ["Geometry", "Linear Algebra", "Physics"],
      "commonUses": ["Perpendicular lines", "Orthogonal vectors", "Normal directions", "Right angles"],
      "related": ["parallel", "orthogonal", "normal"],
      "examples": ["AB ⊥ CD (lines perpendicular)", "u ⊥ v (vectors orthogonal)", "n ⊥ surface (normal vector)"]
    },
    {
      "id": "triangle",
      "name": "Triangle",
      "symbol": "△",
      "category": "Geometric Symbols",
      "description": "Symbol representing a triangle",
      "unicodeValue": "U+25B3",
      "htmlEntity": "&bigtriangleup;",
      "contexts": ["Geometry", "Mathematics", "Change notation"],
      "commonUses": ["Triangle notation", "Change symbol (delta)", "Geometric figures", "Laplace operator"],
      "related": ["delta", "change", "geometry"],
      "examples": ["△ABC (triangle ABC)", "△T = change in temperature", "△ = Laplace operator"]
    },
    {
      "id": "empty-set",
      "name": "Empty Set",
      "symbol": "∅",
      "category": "Set Theory",
      "description": "Symbol representing the empty set",
      "unicodeValue": "U+2205",
      "htmlEntity": "&empty;",
      "contexts": ["Set Theory", "Mathematics", "Logic"],
      "commonUses": ["Empty set", "Null set", "Vacuous truth", "Set operations"],
      "related": ["set", "null", "vacuum"],
      "examples": ["∅ = {} (empty set)", "A ∩ B = ∅ (disjoint sets)", "|∅| = 0 (cardinality zero)"]
    },
    {
      "id": "complement",
      "name": "Complement",
      "symbol": "∁",
      "category": "Set Theory",
      "description": "Symbol for set complement",
      "unicodeValue": "U+2201",
      "htmlEntity": "&comp;",
      "contexts": ["Set Theory", "Logic", "Probability"],
      "commonUses": ["Set complement", "Logical negation", "Probability complement", "Boolean algebra"],
      "related": ["negation", "opposite", "probability"],
      "examples": ["A∁ = complement of A", "P(A∁) = 1 - P(A)", "U \\ A = A∁"]
    },
    {
      "id": "not-element-of",
      "name": "Not Element Of",
      "symbol": "∉",
      "category": "Set Theory",
      "description": "Symbol indicating non-membership in a set",
      "unicodeValue": "U+2209",
      "htmlEntity": "&notin;",
      "contexts": ["Set Theory", "Mathematics", "Logic"],
      "commonUses": ["Non-membership", "Set exclusion", "Logical statements", "Domain restrictions"],
      "related": ["element-of", "membership", "exclusion"],
      "examples": ["x ∉ A (x not in set A)", "0 ∉ ℕ (0 not natural number)", "∞ ∉ ℝ (infinity not real)"]
    },
    {
      "id": "proper-subset",
      "name": "Proper Subset",
      "symbol": "⊂",
      "category": "Set Theory",
      "description": "Symbol indicating proper subset relation",
      "unicodeValue": "U+2282",
      "htmlEntity": "&sub;",
      "contexts": ["Set Theory", "Mathematics", "Logic"],
      "commonUses": ["Proper inclusion", "Strict subset", "Set hierarchy", "Mathematical proofs"],
      "related": ["subset", "inclusion", "proper"],
      "examples": ["A ⊂ B (A proper subset of B)", "ℕ ⊂ ℤ ⊂ ℚ ⊂ ℝ", "{1,2} ⊂ {1,2,3}"]
    },
    {
      "id": "superset",
      "name": "Superset",
      "symbol": "⊇",
      "category": "Set Theory",
      "description": "Symbol indicating superset relation",
      "unicodeValue": "U+2287",
      "htmlEntity": "&supe;",
      "contexts": ["Set Theory", "Mathematics", "Logic"],
      "commonUses": ["Set containment", "Superset relation", "Reverse inclusion", "Category theory"],
      "related": ["subset", "containment", "inclusion"],
      "examples": ["B ⊇ A (B contains A)", "ℝ ⊇ ℚ ⊇ ℤ ⊇ ℕ", "Universal set ⊇ all subsets"]
    },
    {
      "id": "proper-superset",
      "name": "Proper Superset",
      "symbol": "⊃",
      "category": "Set Theory",
      "description": "Symbol indicating proper superset relation",
      "unicodeValue": "U+2283",
      "htmlEntity": "&sup;",
      "contexts": ["Set Theory", "Mathematics", "Logic"],
      "commonUses": ["Proper containment", "Strict superset", "Set hierarchy", "Mathematical proofs"],
      "related": ["proper-subset", "containment", "strict"],
      "examples": ["B ⊃ A (B properly contains A)", "ℝ ⊃ ℚ ⊃ ℤ ⊃ ℕ", "{1,2,3} ⊃ {1,2}"]
    },
    {
      "id": "logical-and",
      "name": "Logical And",
      "symbol": "∧",
      "category": "Logic",
      "description": "Symbol for logical conjunction",
      "unicodeValue": "U+2227",
      "htmlEntity": "&and;",
      "contexts": ["Logic", "Mathematics", "Computer Science"],
      "commonUses": ["Logical AND", "Conjunction", "Boolean algebra", "Predicate logic"],
      "related": ["logical-or", "conjunction", "boolean"],
      "examples": ["P ∧ Q (P and Q)", "x > 0 ∧ x < 10", "true ∧ false = false"]
    },
    {
      "id": "logical-or",
      "name": "Logical Or",
      "symbol": "∨",
      "category": "Logic",
      "description": "Symbol for logical disjunction",
      "unicodeValue": "U+2228",
      "htmlEntity": "&or;",
      "contexts": ["Logic", "Mathematics", "Computer Science"],
      "commonUses": ["Logical OR", "Disjunction", "Boolean algebra", "Predicate logic"],
      "related": ["logical-and", "disjunction", "boolean"],
      "examples": ["P ∨ Q (P or Q)", "x < 0 ∨ x > 10", "true ∨ false = true"]
    },
    {
      "id": "logical-not",
      "name": "Logical Not",
      "symbol": "¬",
      "category": "Logic",
      "description": "Symbol for logical negation",
      "unicodeValue": "U+00AC",
      "htmlEntity": "&not;",
      "contexts": ["Logic", "Mathematics", "Computer Science"],
      "commonUses": ["Logical NOT", "Negation", "Boolean algebra", "Complement"],
      "related": ["negation", "complement", "boolean"],
      "examples": ["¬P (not P)", "¬(x > 0) equivalent to x ≤ 0", "¬true = false"]
    },
    {
      "id": "xor",
      "name": "Exclusive Or",
      "symbol": "⊕",
      "category": "Logic",
      "description": "Symbol for exclusive or (XOR)",
      "unicodeValue": "U+2295",
      "htmlEntity": "&oplus;",
      "contexts": ["Logic", "Computer Science", "Cryptography"],
      "commonUses": ["Exclusive OR", "XOR operation", "Cryptography", "Parity checking"],
      "related": ["logical-or", "exclusive", "crypto"],
      "examples": ["P ⊕ Q (P XOR Q)", "1 ⊕ 1 = 0", "encryption ⊕ key = ciphertext"]
    },
    {
      "id": "nand",
      "name": "NAND",
      "symbol": "⊼",
      "category": "Logic",
      "description": "Symbol for NAND (NOT AND) operation",
      "unicodeValue": "U+22BC",
      "htmlEntity": "&nand;",
      "contexts": ["Logic", "Computer Science", "Digital Circuits"],
      "commonUses": ["NAND gate", "Digital logic", "Boolean functions", "Universal gate"],
      "related": ["logical-and", "negation", "digital"],
      "examples": ["P ⊼ Q = ¬(P ∧ Q)", "NAND is universal gate", "1 ⊼ 1 = 0"]
    },
    {
      "id": "nor",
      "name": "NOR",
      "symbol": "⊽",
      "category": "Logic",
      "description": "Symbol for NOR (NOT OR) operation",
      "unicodeValue": "U+22BD",
      "htmlEntity": "&nor;",
      "contexts": ["Logic", "Computer Science", "Digital Circuits"],
      "commonUses": ["NOR gate", "Digital logic", "Boolean functions", "Universal gate"],
      "related": ["logical-or", "negation", "digital"],
      "examples": ["P ⊽ Q = ¬(P ∨ Q)", "NOR is universal gate", "0 ⊽ 0 = 1"]
    },
    {
      "id": "exists-unique",
      "name": "There Exists Unique",
      "symbol": "∃!",
      "category": "Logic",
      "description": "Symbol for unique existence quantifier",
      "unicodeValue": "U+2203U+0021",
      "htmlEntity": "&exist;!",
      "contexts": ["Logic", "Mathematics", "Set Theory"],
      "commonUses": ["Unique existence", "Uniqueness proofs", "Mathematical definitions", "Existence and uniqueness"],
      "related": ["exists", "unique", "quantifier"],
      "examples": ["∃! x such that f(x) = 0", "∃! identity element", "∃! solution to equation"]
    },
    {
      "id": "models",
      "name": "Models",
      "symbol": "⊨",
      "category": "Logic",
      "description": "Symbol for semantic entailment or models relation",
      "unicodeValue": "U+22A8",
      "htmlEntity": "&models;",
      "contexts": ["Logic", "Model Theory", "Semantics"],
      "commonUses": ["Semantic entailment", "Models relation", "Logical consequence", "Validity"],
      "related": ["entailment", "validity", "semantics"],
      "examples": ["Γ ⊨ φ (Gamma entails phi)", "M ⊨ φ (M models phi)", "⊨ φ (phi is valid)"]
    },
    {
      "id": "proves",
      "name": "Proves",
      "symbol": "⊢",
      "category": "Logic",
      "description": "Symbol for syntactic entailment or proves relation",
      "unicodeValue": "U+22A2",
      "htmlEntity": "&vdash;",
      "contexts": ["Logic", "Proof Theory", "Formal Systems"],
      "commonUses": ["Syntactic entailment", "Proves relation", "Formal proofs", "Derivability"],
      "related": ["models", "proof", "derivation"],
      "examples": ["Γ ⊢ φ (Gamma proves phi)", "⊢ φ (phi is a theorem)", "axioms ⊢ conclusion"]
    },
    {
      "id": "forces",
      "name": "Forces",
      "symbol": "⊩",
      "category": "Logic",
      "description": "Symbol for forcing relation in set theory",
      "unicodeValue": "U+22A9",
      "htmlEntity": "&Vdash;",
      "contexts": ["Set Theory", "Logic", "Forcing"],
      "commonUses": ["Forcing relation", "Set theory", "Independence proofs", "Model construction"],
      "related": ["forcing", "independence", "models"],
      "examples": ["p ⊩ φ (p forces phi)", "forcing conditions", "independence results"]
    },
    {
      "id": "pentagram",
      "name": "Pentagram",
      "symbol": "https://i.postimg.cc/nzFZzbT9/pentagram.png",
      "isImage": true,
      "category": "Geometric Symbols",
      "description": "Five-pointed star symbol used in mathematics, occultism, and various cultural contexts",
      "unicodeValue": null,
      "htmlEntity": null,
      "contexts": ["Geometry", "Mathematics", "Symbolism", "Religion", "Occultism"],
      "commonUses": ["Sacred geometry", "Geometric constructions", "Religious symbolism", "Pentagonal symmetry", "Golden ratio demonstrations"],
      "related": ["star", "polygon", "geometry", "golden-ratio"],
      "examples": ["Regular pentagram construction", "Pentagonal symmetry in nature", "Golden ratio φ ≈ 1.618", "Five-fold rotational symmetry"]
    },
    {
      "id": "ku-klux-klan",
      "name": "Ku Klux Klan",
      "symbol": "https://i.postimg.cc/XJjD7gKN/ku-klux-klan.png",
      "isImage": true,
      "category": "Hate Symbols",
      "description": "Symbol associated with the Ku Klux Klan, a white supremacist organization. This is classified as a hate symbol by the Anti-Defamation League.",
      "unicodeValue": null,
      "htmlEntity": null,
      "contexts": ["Hate Symbols", "Historical", "Civil Rights", "Extremism"],
      "commonUses": ["White supremacist identification", "Historical documentation", "Civil rights education", "Hate crime investigation"],
      "related": ["hate", "supremacy", "historical"],
      "examples": ["Historical civil rights documentation", "Hate symbol identification", "Educational materials on extremism"],
      "isHateSymbol": true
    }
  ]
}